ddnnife_cli/__init__.py
ddnnife_cli/__main__.py
ddnnife_cli-0.1.3.dist-info/licenses/LICENSE
ddnnife_cli-0.1.3.dist-info/METADATA
ddnnife_cli-0.1.3.dist-info/WHEEL
ddnnife_cli-0.1.3.dist-info/entry_points.txt
ddnnife_cli-0.1.3.dist-info/top_level.txt
ddnnife_cli-0.1.3.dist-info/RECORD
