Metadata-Version: 2.4
Name: ddnnife-cli
Version: 0.1.3
Summary: This package provides a CLI wrapper for the ddnnife Docker container.
Author-email: Tobias Heß <tobias.hess@variability.dev>
License-Expression: MIT
Project-URL: Homepage, https://github.com/obddimal/ddnnife-cli
Project-URL: Issues, https://github.com/obddimal/ddnnife-cli/issues
Classifier: Programming Language :: Python :: 3
Classifier: Operating System :: OS Independent
Requires-Python: >=3.9
License-File: LICENSE
Dynamic: license-file
